README.rst
setup.py
elm327/__init__.py
elm327/connection.py
elm327/obd.py
elm327/pcm_values.py
python_elm.egg-info/PKG-INFO
python_elm.egg-info/SOURCES.txt
python_elm.egg-info/dependency_links.txt
python_elm.egg-info/requires.txt
python_elm.egg-info/top_level.txt